{"name":"build-javascript","namedChunkGroups":{"polyfill":{"name":"polyfill","assets":[{"name":"webpack-runtime-69d878cf205dd1a1e449.js","size":5206},{"name":"polyfill-324561e386c0b713fc2c.js","size":85057}],"filteredAssets":0,"assetsSize":90263,"filteredAuxiliaryAssets":2,"auxiliaryAssetsSize":230448},"app":{"name":"app","assets":[{"name":"webpack-runtime-69d878cf205dd1a1e449.js","size":5206},{"name":"styles.f10c8d6542dd93afda41.css","size":1170501},{"name":"framework-77be70eb17ef64ff8367.js","size":24195},{"name":"3f943334-bf52df274cd7f0b28e8d.js","size":8458},{"name":"379b34f3-732e21e22fba8101e5d4.js","size":16473},{"name":"ff106bf9-438ed314805d7d9c3767.js","size":14286},{"name":"bca8bde3-40271fcd1ec6afc61b8b.js","size":16817},{"name":"app-5c09c825355e39aa0b54.js","size":265459}],"filteredAssets":0,"assetsSize":1521395,"filteredAuxiliaryAssets":7,"auxiliaryAssetsSize":1207040},"component---node-modules-adobe-gatsby-theme-aio-src-pages-404-md":{"name":"component---node-modules-adobe-gatsby-theme-aio-src-pages-404-md","assets":[{"name":"styles.f10c8d6542dd93afda41.css","size":1170501},{"name":"b6f3ea4c-d26080b07df96c35191d.js","size":8819},{"name":"f5cc1685-bae263d934dfa1ee4df0.js","size":6221},{"name":"5e65052d-31673454626ea91bc648.js","size":7274},{"name":"8b61fb39-85e9244615ce26b2da9d.js","size":6535},{"name":"2dee68d8-74b469d30f5dbb1c14ad.js","size":8011},{"name":"commons-715051d1517f2394f777.js","size":117847},{"name":"component---node-modules-adobe-gatsby-theme-aio-src-pages-404-md-e01530a3baa9b605665d.js","size":1113}],"filteredAssets":0,"assetsSize":1326321,"filteredAuxiliaryAssets":7,"auxiliaryAssetsSize":449042},"component---src-pages-api-index-md":{"name":"component---src-pages-api-index-md","assets":[{"name":"styles.f10c8d6542dd93afda41.css","size":1170501},{"name":"b6f3ea4c-d26080b07df96c35191d.js","size":8819},{"name":"f5cc1685-bae263d934dfa1ee4df0.js","size":6221},{"name":"5e65052d-31673454626ea91bc648.js","size":7274},{"name":"8b61fb39-85e9244615ce26b2da9d.js","size":6535},{"name":"2dee68d8-74b469d30f5dbb1c14ad.js","size":8011},{"name":"commons-715051d1517f2394f777.js","size":117847},{"name":"component---src-pages-api-index-md-4a50a47b0a0e6b10f94c.js","size":1715}],"filteredAssets":0,"assetsSize":1326923,"filteredAuxiliaryAssets":7,"auxiliaryAssetsSize":449625},"component---src-pages-index-md":{"name":"component---src-pages-index-md","assets":[{"name":"styles.f10c8d6542dd93afda41.css","size":1170501},{"name":"b6f3ea4c-d26080b07df96c35191d.js","size":8819},{"name":"f5cc1685-bae263d934dfa1ee4df0.js","size":6221},{"name":"5e65052d-31673454626ea91bc648.js","size":7274},{"name":"8b61fb39-85e9244615ce26b2da9d.js","size":6535},{"name":"2dee68d8-74b469d30f5dbb1c14ad.js","size":8011},{"name":"commons-715051d1517f2394f777.js","size":117847},{"name":"component---src-pages-index-md-e5ff2e09f66475c8ab1a.js","size":22822}],"filteredAssets":0,"assetsSize":1348030,"filteredAuxiliaryAssets":7,"auxiliaryAssetsSize":484555},"component---src-pages-support-index-md":{"name":"component---src-pages-support-index-md","assets":[{"name":"styles.f10c8d6542dd93afda41.css","size":1170501},{"name":"b6f3ea4c-d26080b07df96c35191d.js","size":8819},{"name":"f5cc1685-bae263d934dfa1ee4df0.js","size":6221},{"name":"5e65052d-31673454626ea91bc648.js","size":7274},{"name":"8b61fb39-85e9244615ce26b2da9d.js","size":6535},{"name":"2dee68d8-74b469d30f5dbb1c14ad.js","size":8011},{"name":"commons-715051d1517f2394f777.js","size":117847},{"name":"component---src-pages-support-index-md-722f83aa8281833c8f5b.js","size":9796}],"filteredAssets":0,"assetsSize":1335004,"filteredAuxiliaryAssets":7,"auxiliaryAssetsSize":464828},"component---src-pages-usage-index-md":{"name":"component---src-pages-usage-index-md","assets":[{"name":"styles.f10c8d6542dd93afda41.css","size":1170501},{"name":"b6f3ea4c-d26080b07df96c35191d.js","size":8819},{"name":"f5cc1685-bae263d934dfa1ee4df0.js","size":6221},{"name":"5e65052d-31673454626ea91bc648.js","size":7274},{"name":"8b61fb39-85e9244615ce26b2da9d.js","size":6535},{"name":"2dee68d8-74b469d30f5dbb1c14ad.js","size":8011},{"name":"commons-715051d1517f2394f777.js","size":117847},{"name":"component---src-pages-usage-index-md-ca670b835766f21404b6.js","size":5646}],"filteredAssets":0,"assetsSize":1330854,"filteredAuxiliaryAssets":7,"auxiliaryAssetsSize":453939}},"assetsByChunkName":{"polyfill":["webpack-runtime-69d878cf205dd1a1e449.js","polyfill-324561e386c0b713fc2c.js"],"app":["webpack-runtime-69d878cf205dd1a1e449.js","styles.f10c8d6542dd93afda41.css","framework-77be70eb17ef64ff8367.js","3f943334-bf52df274cd7f0b28e8d.js","379b34f3-732e21e22fba8101e5d4.js","ff106bf9-438ed314805d7d9c3767.js","bca8bde3-40271fcd1ec6afc61b8b.js","app-5c09c825355e39aa0b54.js"],"component---node-modules-adobe-gatsby-theme-aio-src-pages-404-md":["styles.f10c8d6542dd93afda41.css","b6f3ea4c-d26080b07df96c35191d.js","f5cc1685-bae263d934dfa1ee4df0.js","5e65052d-31673454626ea91bc648.js","8b61fb39-85e9244615ce26b2da9d.js","2dee68d8-74b469d30f5dbb1c14ad.js","commons-715051d1517f2394f777.js","component---node-modules-adobe-gatsby-theme-aio-src-pages-404-md-e01530a3baa9b605665d.js"],"component---src-pages-api-index-md":["styles.f10c8d6542dd93afda41.css","b6f3ea4c-d26080b07df96c35191d.js","f5cc1685-bae263d934dfa1ee4df0.js","5e65052d-31673454626ea91bc648.js","8b61fb39-85e9244615ce26b2da9d.js","2dee68d8-74b469d30f5dbb1c14ad.js","commons-715051d1517f2394f777.js","component---src-pages-api-index-md-4a50a47b0a0e6b10f94c.js"],"component---src-pages-index-md":["styles.f10c8d6542dd93afda41.css","b6f3ea4c-d26080b07df96c35191d.js","f5cc1685-bae263d934dfa1ee4df0.js","5e65052d-31673454626ea91bc648.js","8b61fb39-85e9244615ce26b2da9d.js","2dee68d8-74b469d30f5dbb1c14ad.js","commons-715051d1517f2394f777.js","component---src-pages-index-md-e5ff2e09f66475c8ab1a.js"],"component---src-pages-support-index-md":["styles.f10c8d6542dd93afda41.css","b6f3ea4c-d26080b07df96c35191d.js","f5cc1685-bae263d934dfa1ee4df0.js","5e65052d-31673454626ea91bc648.js","8b61fb39-85e9244615ce26b2da9d.js","2dee68d8-74b469d30f5dbb1c14ad.js","commons-715051d1517f2394f777.js","component---src-pages-support-index-md-722f83aa8281833c8f5b.js"],"component---src-pages-usage-index-md":["styles.f10c8d6542dd93afda41.css","b6f3ea4c-d26080b07df96c35191d.js","f5cc1685-bae263d934dfa1ee4df0.js","5e65052d-31673454626ea91bc648.js","8b61fb39-85e9244615ce26b2da9d.js","2dee68d8-74b469d30f5dbb1c14ad.js","commons-715051d1517f2394f777.js","component---src-pages-usage-index-md-ca670b835766f21404b6.js"]},"childAssetsByChunkName":{}}